FlowSOM/__init__.py
FlowSOM/_cluster_algorithms.py
FlowSOM/_consensus_cluster.py
FlowSOM/_flowsom.py
flowsom_clustering-0.0.7.dist-info/METADATA
flowsom_clustering-0.0.7.dist-info/WHEEL
flowsom_clustering-0.0.7.dist-info/licenses/LICENSE
flowsom_clustering-0.0.7.dist-info/RECORD
