Metadata-Version: 2.1
Name: flowsom-clustering
Version: 0.0.7
Summary: A Python implementation of FlowSOM algorithm with parallelized consensus metaclustering
Project-URL: Homepage, https://github.com/TarikExner/FlowSOM/
Project-URL: Bug Tracker, https://github.com/TarikExner/FlowSOM/
Author-email: Tarik Exner <Tarik.Exner@gmail.com>
License-File: LICENSE
Classifier: License :: OSI Approved :: MIT License
Classifier: Operating System :: OS Independent
Classifier: Programming Language :: Python :: 3
Classifier: Topic :: Scientific/Engineering :: Bio-Informatics
Requires-Python: >=3.7
Requires-Dist: minisom
Requires-Dist: numpy
Requires-Dist: pandas
Requires-Dist: scikit-learn
